matbox/MT.py
matbox/__init__.py
matbox/CodeViewer/CodeViewer.py
matbox/CodeViewer/__init__.py
matbox/CodeViewer/grammar_tool.py
matbox/HomePage/__init__.py
matbox/HomePage/mainface.py
matbox/Setting/Settings.py
matbox/Setting/__init__.py
matbox/Setting/_load_or_dump_config.py
matbox/Source/QSS/main.qss
matbox/Source/cfg/config.yaml
matbox/Source/h5/main.html
matbox/Source/h5/readme.svg
matbox/Source/h5/tutorial.html
matbox/Source/img/logo.ico
matbox/Source/mouseCursor/alternate.cur
matbox/Source/mouseCursor/busy.cur
matbox/Source/mouseCursor/diagonal1.cur
matbox/Source/mouseCursor/diagonal2.cur
matbox/Source/mouseCursor/handwriting.cur
matbox/Source/mouseCursor/help.cur
matbox/Source/mouseCursor/horizontal.cur
matbox/Source/mouseCursor/link.cur
matbox/Source/mouseCursor/move.cur
matbox/Source/mouseCursor/normal.cur
matbox/Source/mouseCursor/precision.cur
matbox/Source/mouseCursor/table.cur
matbox/Source/mouseCursor/text.cur
matbox/Source/mouseCursor/unavailable.cur
matbox/Source/mouseCursor/vertical.cur
matbox/Source/mouseCursor/working.cur
matbox/Source/tutorial/axes design.mtml
matbox/Source/tutorial/bar chart.mtml
matbox/Source/tutorial/box plot.mtml
matbox/Source/tutorial/color settings.mtml
matbox/Source/tutorial/font settings.mtml
matbox/Source/tutorial/format-mtml.mtml
matbox/Source/tutorial/heatmap.mtml
matbox/Source/tutorial/histogram.mtml
matbox/Source/tutorial/labels settings.mtml
matbox/Source/tutorial/line chart.mtml
matbox/Source/tutorial/lines settings.mtml
matbox/Source/tutorial/multi-subplots.mtml
matbox/Source/tutorial/pie chart.mtml
matbox/Source/tutorial/points settings.mtml
matbox/Source/tutorial/polar plot.mtml
matbox/Source/tutorial/scatter plot.mtml
matbox/Source/tutorial/the-layout-of-mtml-file.mtml
matbox/Source/tutorial/titles settings.mtml
matbox/TreeItems/__init__.py
matbox/TreeItems/basetree.py
matbox-1.0.7.dist-info/METADATA
matbox-1.0.7.dist-info/WHEEL
matbox-1.0.7.dist-info/entry_points.txt
matbox-1.0.7.dist-info/top_level.txt
matbox-1.0.7.dist-info/RECORD
